habot/__init__.py
habot/bot.py
habot-0.0.3.dist-info/METADATA
habot-0.0.3.dist-info/WHEEL
habot-0.0.3.dist-info/licenses/LICENSE
habot-0.0.3.dist-info/RECORD
