Metadata-Version: 2.1
Name: habot
Version: 0.0.3
Summary: A Telegram bot wrapper to run HA bots
Project-URL: Homepage, https://github.com:juuso22/habot
Author: Juuso22
License: MIT License
License-File: LICENSE
Classifier: License :: OSI Approved :: MIT License
Classifier: Programming Language :: Python :: 3
Requires-Python: >=3.10
